discord_py_buttons/__init__.py
discord_py_buttons/buttons.py
discord_py_buttons/client.py
discord_py_buttons/receive.py
discord_py_buttons/tools.py
discord_py_buttons-1.1.2.dist-info/LICENSE
discord_py_buttons-1.1.2.dist-info/METADATA
discord_py_buttons-1.1.2.dist-info/WHEEL
discord_py_buttons-1.1.2.dist-info/top_level.txt
discord_py_buttons-1.1.2.dist-info/RECORD
