Metadata-Version: 2.1
Name: discord-py-buttons
Version: 1.1.2
Summary: A discord button handler for discord.py
Home-page: https://github.com/KusoRedsto/discord_py_buttons
Author: 404kuso, RedstoneZockt
Author-email: bellou9022@gmail.com, redstoneprofihd@gmail.com
License: UNKNOWN
Platform: UNKNOWN
Classifier: Programming Language :: Python :: 3
Requires-Python: >=3.9
License-File: LICENSE
